mongodb_client/__init__.py
mongodb_client/mongodb.py
mongodb_client-0.2.dist-info/METADATA
mongodb_client-0.2.dist-info/WHEEL
mongodb_client-0.2.dist-info/top_level.txt
mongodb_client-0.2.dist-info/RECORD
