Metadata-Version: 2.1
Name: mongodb-client
Version: 0.2
Summary: A Python module to interact with a MongoDB database via HTTP requests.
Home-page: https://github.com/luisresende13/mongodb_client
Author: Luis Resende Silva
Author-email: luisresende13@gmail.com
Classifier: Programming Language :: Python :: 3
Classifier: License :: OSI Approved :: MIT License
Classifier: Operating System :: OS Independent
Requires-Python: >=3.6
Requires-Dist: requests
